<?xml version="1.0" encoding="utf-8"?>
<ConstraintsData xmlns:xsd="http://www.w3.org/2001/XMLSchema" xmlns:xsi="http://www.w3.org/2001/XMLSchema-instance">
  <FlattenedNetName2ConstraintNetId />
  <CNets />
  <CNetClasses />
  <CDifferentialPairs />
  <CDifferentialPairClasses />
  <CPinPairs />
  <CxSigClasses />
  <CxNets />
  <CXNetClasses />
  <ConstraintClearancesMatrix>
    <CCMFromScopes>
      <CCMFromScope Id="ac3c6e2d-003c-418a-8d5b-bf4b60522e2e">
        <ConstraintObject Id="00000000-0000-0000-0000-000000000000" />
        <CCMToScopes>
          <CCMToScope Id="ba43c01b-66bf-4b8b-8866-8b4593e6661a" SetId="00000000-0000-0000-0000-000000000000">
            <ConstraintObject Id="00000000-0000-0000-0000-000000000000" />
            <DefaultConstraintClearancesMatrixConstraint Id="00000000-0000-0000-0000-000000000000" Kind="0" Name="" Description="" Scope1="" Scope2="" Attributes="" LayerType="0" LayerId="0" />
            <CCMConstraints />
          </CCMToScope>
        </CCMToScopes>
      </CCMFromScope>
    </CCMFromScopes>
  </ConstraintClearancesMatrix>
  <ConstraintSameNetClearancesMatrix>
    <CCMFromScopes />
  </ConstraintSameNetClearancesMatrix>
  <CSets />
  <CClearancesMatrixSets />
</ConstraintsData>